ansio/__init__.py
ansio/colors.py
ansio/input.py
ansio/test_ansio.py
ansio-0.0.2.dist-info/METADATA
ansio-0.0.2.dist-info/WHEEL
ansio-0.0.2.dist-info/licenses/LICENSE
ansio-0.0.2.dist-info/RECORD
